{
  "cacheBootResources": true,
  "debugBuild": false,
  "entryAssembly": "CSharpToTypeScript.Blazor",
  "linkerEnabled": true,
  "resources": {
    "assembly": {
      "CSharpToTypeScript.Blazor.dll": "sha256-KvWngcC\/zl8BWw6snV4cKbgEZuoj\/kwcFOBT\/2OQgLg=",
      "CSharpToTypeScript.Core.dll": "sha256-PEL4zajk5r5M8FeAatTtGTy8U2MeNe30b95pKFpZET8=",
      "Microsoft.AspNetCore.Components.dll": "sha256-TFaNpRO3L2eg\/5BDPpaXFxCk0nPBaDJZgt+oAD+qNrA=",
      "Microsoft.AspNetCore.Components.Forms.dll": "sha256-ns2XNJYpmIKW9p5d4WWqErTMc\/mm7fHqoYZvbN4TcgI=",
      "Microsoft.AspNetCore.Components.Web.dll": "sha256-9+9NTuEeiDPGARzHWN\/zVcn4osAlBbx+RimPy6\/j6O0=",
      "Microsoft.AspNetCore.Components.WebAssembly.dll": "sha256-JLApq212n3FyhSUGePOaCU4Xz8NU74ehw8uKeXWqARY=",
      "Microsoft.Bcl.AsyncInterfaces.dll": "sha256-jzHgXWAvWMkKIGFjZoT84tbe72E+H7CvTr\/Dryh4QPs=",
      "Microsoft.CodeAnalysis.CSharp.dll": "sha256-rwb5E1rs3JVTtyL1OJyOW\/7cac3ca18qOSpP8twvVvg=",
      "Microsoft.CodeAnalysis.dll": "sha256-hJvAs8m+0nVWTn8E+gUyK6EvGR6ArwcCmtZS+P3stAY=",
      "Microsoft.Extensions.Configuration.Abstractions.dll": "sha256-3k2sI4tPo0CBV3rENthP0TqQcgAMI1IoDaKJ25QK23g=",
      "Microsoft.Extensions.Configuration.dll": "sha256-PzIGJC\/jGwKn1dGyFeLbE00OI+qfKO\/zIzNGa7Wji64=",
      "Microsoft.Extensions.DependencyInjection.Abstractions.dll": "sha256-JGRpWtW1nG6WeUJHJ1ffUwfmr6oJXEoR2m7QCMpmOX4=",
      "Microsoft.Extensions.DependencyInjection.dll": "sha256-Qy\/Kg\/zWCAxK58YmzUEoTAP7iRJ5Djnnqv6tNz5ZYaA=",
      "Microsoft.Extensions.Logging.Abstractions.dll": "sha256-fmfbryObztIOVope5D1GawdzkX7OXchT0TGLmcrVorc=",
      "Microsoft.Extensions.Primitives.dll": "sha256-46Jlt6Rjy5vRIMHrgDeY8qL6XejlRQjE2Uynd9qYEDk=",
      "Microsoft.JSInterop.dll": "sha256-CJ0jnf2G21cOvZYQt\/4NVkv642Xz8fLQyPnHvcfP3D4=",
      "Microsoft.JSInterop.WebAssembly.dll": "sha256-VP8179q6KlTFT\/O0r6zq3Il8a0P7HOsHY2h35s5Lpng=",
      "Mono.Security.dll": "sha256-bzP3lUrC\/gcBLd1LkfnS+y9PjqZ5dJ\/4oPwrIW2A3uk=",
      "mscorlib.dll": "sha256-rWqIzGDYGOE6Ly7TYG8jgGnRhx5LPk6PgRQfLwj0\/5k=",
      "System.Collections.Immutable.dll": "sha256-DOaZ22nQEN6LBtQ65AtACNNB8eoorCD\/3s2Br\/Qx+Gw=",
      "System.ComponentModel.DataAnnotations.dll": "sha256-a79cgSFDpm2ck067rlMIi89tj0IJNjyNJDVErqLAgEk=",
      "System.Core.dll": "sha256-80ZYkVgFV\/LUOw4y7aNCJyeyKVfzasj3lJooTlYu9F0=",
      "System.dll": "sha256-4XD1DgZn9LIP4fhzQA0aikdWyEEOVwTcLj2axbRFwes=",
      "System.Net.Http.dll": "sha256-U0W42Hjwk4YnDfzg5\/XQSF3Ah27+I4oCgZKWelSOrUU=",
      "System.Numerics.dll": "sha256-lMSCCtbDy7Xrwoi3ld\/rI5ULV9wyWp3KaHRC1VA7cSc=",
      "System.Reflection.Metadata.dll": "sha256-QqUxhMMC3NaoMH6mMWz8Mwh2T7Dkq39A8tvsiuD3x1g=",
      "System.Runtime.CompilerServices.Unsafe.dll": "sha256-iOhnfNzDIXaMoHZNgBBuGGx0gyyc4UHWUv62wWTcpRs=",
      "System.Text.Encoding.CodePages.dll": "sha256-cXFT\/zksEKrNGOaxFlHB+6TdXm0yRCH8HQKBGlg++K4=",
      "System.Text.Encodings.Web.dll": "sha256-6Kk+drDSZrf0Bea22yFR2o2OPSzumOe8l0tAQF0eiYA=",
      "System.Text.Json.dll": "sha256-nSUC896lQ612wwXNHV+F3N1+mzHZNf6mf8z5GSn8qb8=",
      "System.Xml.dll": "sha256-SDpOQ5CNtbiT8SQG5v2NU2QgF3lJdjnX2thhH4r+Z\/8=",
      "System.Xml.Linq.dll": "sha256-u9UkepY4dOqenkk1oVNhjcIn\/U43Nf\/k1t5nXGWCOrA=",
      "WebAssembly.Bindings.dll": "sha256-dEUaAiZDUW\/UTwTrjZdUCaa58VLaJyt1aDNh8Mw2zIg=",
      "WebAssembly.Net.Http.dll": "sha256-2fGSjhQbcEnSerkjpKU7D\/tx\/DLgTRJyjG6YjbF40SA="
    },
    "runtime": {
      "dotnet.3.2.0-preview2.20159.2.js": "sha256-80Q7rIpqLxXzuMWqtC+FCBNrG15kR\/r+ba08n2TpQO0=",
      "dotnet.wasm": "sha256-TwiabWTQ0R8CJeRzc59eU16DKfcf2p8PIvZsyWF7\/8M="
    }
  }
}